README.md
setup.py
vdog/ProcessConstructor.py
vdog/VdogDriver.py
vdog/__init__.py
vdog.egg-info/PKG-INFO
vdog.egg-info/SOURCES.txt
vdog.egg-info/dependency_links.txt
vdog.egg-info/top_level.txt